AUTHORS.rst
CONTRIBUTING.rst
HISTORY.rst
LICENSE
MANIFEST.in
README.rst
setup.cfg
setup.py
cheese/__init__.py
cheese/cheese.py
cheese.egg-info/PKG-INFO
cheese.egg-info/SOURCES.txt
cheese.egg-info/dependency_links.txt
cheese.egg-info/not-zip-safe
cheese.egg-info/top_level.txt