Metadata-Version: 1.1
Name: cheese
Version: 0.1.0
Summary: My first Python package using cookiecutter.
Home-page: https://github.com/fengwangjiang/cheese
Author: Xingde Jiang
Author-email: jiangxingde@gmail.com
License: BSD
Keywords: cheese
Platform: UNKNOWN
Classifier: Development Status :: 2 - Pre-Alpha
Classifier: Intended Audience :: Developers
Classifier: License :: OSI Approved :: BSD License
Classifier: Natural Language :: English
Classifier: Programming Language :: Python :: 2
Classifier: Programming Language :: Python :: 2.6
Classifier: Programming Language :: Python :: 2.7
Classifier: Programming Language :: Python :: 3
Classifier: Programming Language :: Python :: 3.3
